{
	"name": "csv1",
	"properties": {
		"linkedServiceName": {
			"referenceName": "AzureBlobStorage1",
			"type": "LinkedServiceReference"
		},
		"annotations": [],
		"type": "DelimitedText",
		"typeProperties": {
			"location": {
				"type": "AzureBlobStorageLocation",
				"fileName": "emp1.csv",
				"container": "input-src"
			},
			"columnDelimiter": ",",
			"escapeChar": "\\",
			"firstRowAsHeader": true,
			"quoteChar": "\""
		},
		"schema": [
			{
				"name": "emp_id",
				"type": "String"
			},
			{
				"name": "emp_name",
				"type": "String"
			},
			{
				"name": "emp_salary ",
				"type": "String"
			},
			{
				"name": "manager",
				"type": "String"
			}
		]
	},
	"type": "Microsoft.DataFactory/factories/datasets"
}